app/__init__.py
app/backend_pre_start.py
app/celeryworker_pre_start.py
app/dnada_cli.py
app/initial_data.py
app/main.py
app/tests_pre_start.py
app/utils.py
app/worker.py
app/api/__init__.py
app/api/deps.py
app/api/api_v1/__init__.py
app/api/api_v1/api.py
app/api/api_v1/endpoints/__init__.py
app/api/api_v1/endpoints/assemblys.py
app/api/api_v1/endpoints/banner.py
app/api/api_v1/endpoints/constructs.py
app/api/api_v1/endpoints/crudapi.py
app/api/api_v1/endpoints/designs.py
app/api/api_v1/endpoints/digests.py
app/api/api_v1/endpoints/experiments.py
app/api/api_v1/endpoints/instructions.py
app/api/api_v1/endpoints/login.py
app/api/api_v1/endpoints/oligos.py
app/api/api_v1/endpoints/parts.py
app/api/api_v1/endpoints/pcrs.py
app/api/api_v1/endpoints/runs.py
app/api/api_v1/endpoints/standalone.py
app/api/api_v1/endpoints/synths.py
app/api/api_v1/endpoints/users.py
app/api/api_v1/endpoints/utils.py
app/api/api_v1/endpoints/validate.py
app/api/api_v1/endpoints/workflow.py
app/api/utils/__init__.py
app/api/utils/assemblyrun_helper.py
app/api/utils/db.py
app/api/utils/ngs.py
app/api/utils/pcrrun_helper.py
app/api/utils/post_automation.py
app/api/utils/pre_j5_to_echo.py
app/api/utils/pydantic_form_decorator.py
app/api/utils/results_toolbox.py
app/api/utils/sequencingrun_helper.py
app/api/utils/sql.py
app/api/utils/time.py
app/core/__init__.py
app/core/assembly.py
app/core/autoprotocols.py
app/core/celery_app.py
app/core/colony_pcr.py
app/core/condense_designs.py
app/core/config.py
app/core/dna_utils.py
app/core/echo.py
app/core/j5.py
app/core/j5_to_echo.py
app/core/j5_to_echo_utils.py
app/core/pcr_update.py
app/core/picking.py
app/core/plating_utils.py
app/core/process_design.py
app/core/security.py
app/core/visualizations.py
app/core/workflow_readme.py
app/crud/__init__.py
app/crud/base.py
app/crud/crud_assembly.py
app/crud/crud_banner.py
app/crud/crud_construct.py
app/crud/crud_design.py
app/crud/crud_digest.py
app/crud/crud_experiment.py
app/crud/crud_instruction.py
dnada-0.1.2.dist-info/LICENSE
dnada-0.1.2.dist-info/METADATA
dnada-0.1.2.dist-info/WHEEL
dnada-0.1.2.dist-info/entry_points.txt
dnada-0.1.2.dist-info/top_level.txt
dnada-0.1.2.dist-info/RECORD
