Metadata-Version: 2.1
Name: dnada
Version: 0.1.2
Summary: An application for creating customized synthetic biology automation instructions
Home-page: https://github.com/JBEI/dnada
Maintainer: Alberto Nava
Maintainer-email: alberto_nava@berkeley.edu
License: Apache 2.0
Classifier: Programming Language :: Python :: 3
Classifier: License :: OSI Approved :: Apache Software License
Classifier: Operating System :: OS Independent
Requires-Python: >=3.9
License-File: LICENSE
Requires-Dist: autoprotocol
Requires-Dist: alembic
Requires-Dist: bcrypt
Requires-Dist: biopython
Requires-Dist: celery
Requires-Dist: emails
Requires-Dist: email-validator
Requires-Dist: fastapi
Requires-Dist: k-means-constrained
Requires-Dist: openpyxl
Requires-Dist: pandas
Requires-Dist: pandera
Requires-Dist: passlib
Requires-Dist: psycopg2-binary
Requires-Dist: pydantic
Requires-Dist: python-jose
Requires-Dist: pytz
Requires-Dist: raven
Requires-Dist: requests
Requires-Dist: scipy
Requires-Dist: seaborn
Requires-Dist: SQLAlchemy
Requires-Dist: tenacity
Requires-Dist: typer
